fastapi_bootstrap_utils/__init__.py
fastapi_bootstrap_utils/console_helper.py
fastapi_bootstrap_utils/create_app.py
fastapi_bootstrap_utils/file_utils.py
fastapi_bootstrap_utils/make_shell_scripts_and_aliases.py
fastapi_bootstrap_utils/progress_bar.py
fastapi_bootstrap_utils/conf/config.yaml
fastapi_bootstrap_utils/templates/helper.py.tt
fastapi_bootstrap_utils/templates/main.py.tt
fastapi_bootstrap_utils/templates/router.py.tt
fastapi_bootstrap_utils-0.1.0.dist-info/AUTHORS.rst
fastapi_bootstrap_utils-0.1.0.dist-info/METADATA
fastapi_bootstrap_utils-0.1.0.dist-info/WHEEL
fastapi_bootstrap_utils-0.1.0.dist-info/entry_points.txt
fastapi_bootstrap_utils-0.1.0.dist-info/top_level.txt
fastapi_bootstrap_utils-0.1.0.dist-info/RECORD
